LICENCE
MANIFEST.in
setup.py
Atom_avatar.egg-info/PKG-INFO
Atom_avatar.egg-info/SOURCES.txt
Atom_avatar.egg-info/dependency_links.txt
Atom_avatar.egg-info/top_level.txt
avatar/README.md
avatar/__init__.py
avatar/index.py
avatar/male_back.json
avatar/male_beard.json
avatar/male_brows.json
avatar/male_clothes.json
avatar/male_ears.json
avatar/male_eyes.json
avatar/male_face.json
avatar/male_glasses.json
avatar/male_hair.json
avatar/male_iris.json
avatar/male_mouth.json
avatar/male_mustache.json
avatar/male_nose.json
avatar/male_start.json
avatar/sample.svg
avatar/stadium_image.jpeg
avatar/templates/base.svg