Metadata-Version: 2.1
Name: Atom-avatar
Version: 0.0.2
Summary: python avater maker with avatermaker.com svg
Author: Quadri Tosin Micheal
License-File: LICENCE
